{
  "users": [
    {
      "id": 1,
      "name": "John Doe",
      "email": "johndoe@example.com"
    },
    {
      "id": 2,
      "name": "Jane Smith",
      "email": "janesmith@example.com"
    },
    {
      "id": 3,
      "name": "Michael Johnson",
      "email": "michaeljohnson@example.com"
    },
    {
      "id": 4,
      "name": "Emily Davis",
      "email": "emilydavis@example.com"
    },
    {
      "id": 5,
      "name": "David Wilson",
      "email": "davidwilson@example.com"
    },
    {
      "id": 6,
      "name": "Sarah Thompson",
      "email": "sarahthompson@example.com"
    },
    {
      "id": 7,
      "name": "Daniel Martinez",
      "email": "danielmartinez@example.com"
    },
    {
      "id": 8,
      "name": "Olivia Anderson",
      "email": "oliviaanderson@example.com"
    },
    {
      "id": 9,
      "name": "James Taylor",
      "email": "jamestaylor@example.com"
    },
    {
      "id": 10,
      "name": "Sophia Thomas",
      "email": "sophiathomas@example.com"
    },
    {
      "id": 11,
      "name": "Benjamin Hernandez",
      "email": "benjaminhernandez@example.com"
    },
    {
      "id": 12,
      "name": "Ava Moore",
      "email": "avamoore@example.com"
    },
    {
      "id": 13,
      "name": "William Clark",
      "email": "williamclark@example.com"
    },
    {
      "id": 14,
      "name": "Mia Lewis",
      "email": "mialewis@example.com"
    },
    {
      "id": 15,
      "name": "Ethan Walker",
      "email": "ethanwalker@example.com"
    }
  ]
}
